LICENSE
README.rst
setup.py
furuta_plot/__init__.py
furuta_plot/backend.py
furuta_plot/furuta_plot.py
furuta_plot/types.py
furuta_plot.egg-info/PKG-INFO
furuta_plot.egg-info/SOURCES.txt
furuta_plot.egg-info/dependency_links.txt
furuta_plot.egg-info/requires.txt
furuta_plot.egg-info/top_level.txt