Metadata-Version: 2.1
Name: furuta-plot
Version: 0.0.3
Summary: A furuta pendulum plotter based on matplotlib.
Home-page: https://github.com/johnwikman/furuta-plot
Author: John Wikman
License: MIT License
Keywords: ipm,furuta,plot,visualizer
Classifier: Programming Language :: Python :: 3
Classifier: License :: OSI Approved :: MIT License
Classifier: Operating System :: OS Independent
License-File: LICENSE
